MANIFEST.in
README.txt
bootstrap.py
buildout.cfg
setup.cfg
setup.py
docs/Makefile
docs/conf.py
docs/index.rst
docs/make.bat
docs/sphinxusers.jpg
src/AUTHORS.txt
src/HISTORY.txt
src/LICENSE.txt
src/README.txt
src/TODOS.txt
src/sphinxjp/__init__.py
src/sphinxjp.themes.htmlslide.egg-info/PKG-INFO
src/sphinxjp.themes.htmlslide.egg-info/SOURCES.txt
src/sphinxjp.themes.htmlslide.egg-info/dependency_links.txt
src/sphinxjp.themes.htmlslide.egg-info/entry_points.txt
src/sphinxjp.themes.htmlslide.egg-info/namespace_packages.txt
src/sphinxjp.themes.htmlslide.egg-info/not-zip-safe
src/sphinxjp.themes.htmlslide.egg-info/requires.txt
src/sphinxjp.themes.htmlslide.egg-info/top_level.txt
src/sphinxjp/themes/__init__.py
src/sphinxjp/themes/htmlslide/__init__.py
src/sphinxjp/themes/htmlslide/templates/htmlslide/AUTHORS.txt
src/sphinxjp/themes/htmlslide/templates/htmlslide/LICENSE.txt
src/sphinxjp/themes/htmlslide/templates/htmlslide/genindex.html
src/sphinxjp/themes/htmlslide/templates/htmlslide/layout.html
src/sphinxjp/themes/htmlslide/templates/htmlslide/page.html
src/sphinxjp/themes/htmlslide/templates/htmlslide/search.html
src/sphinxjp/themes/htmlslide/templates/htmlslide/theme.conf
src/sphinxjp/themes/htmlslide/templates/htmlslide/static/basic.css
src/sphinxjp/themes/htmlslide/templates/htmlslide/static/default.css
src/sphinxjp/themes/htmlslide/templates/htmlslide/static/jquery.js
src/sphinxjp/themes/htmlslide/templates/htmlslide/static/prettify.css
src/sphinxjp/themes/htmlslide/templates/htmlslide/static/prettify.js
src/sphinxjp/themes/htmlslide/templates/htmlslide/static/slide.css
src/sphinxjp/themes/htmlslide/templates/htmlslide/static/slide.js