Metadata-Version: 1.0
Name: sphinxjp.themes.htmlslide
Version: 0.1.3
Summary: A sphinx theme for generate HTML Slide presentation. #sphinxjp
Home-page: http://bitbucket.org/shimizukawa/sphinxjp.themes.htmlslide
Author: Takayuki SHIMIZUKAWA
Author-email: shimizukawa at gmail dot com
License: MIT
Keywords: sphinx,reStructuredText,presentation
Platform: UNKNOWN
Classifier: Development Status :: 4 - Beta
Classifier: License :: OSI Approved :: MIT License
Classifier: Programming Language :: Python
Classifier: Topic :: Software Development
Classifier: Topic :: Software Development :: Documentation
Classifier: Topic :: Text Processing :: Markup
